walnats/__init__.py
walnats/_constants.py
walnats/_context.py
walnats/_errors.py
walnats/_services.py
walnats/_tasks.py
walnats/py.typed
walnats/types.py
walnats/_actors/__init__.py
walnats/_actors/_actor.py
walnats/_actors/_connection.py
walnats/_actors/_execute_in.py
walnats/_actors/_priority.py
walnats/_actors/_registry.py
walnats/_events/__init__.py
walnats/_events/_clock.py
walnats/_events/_cloud_event.py
walnats/_events/_connection.py
walnats/_events/_event.py
walnats/_events/_limits.py
walnats/_events/_registry.py
walnats/_linter/__init__.py
walnats/_linter/_checker.py
walnats/_linter/_finders.py
walnats/_linter/_violation.py
walnats/decorators/__init__.py
walnats/decorators/_filter_time.py
walnats/decorators/_rate_limit.py
walnats/decorators/_require.py
walnats/decorators/_suppress.py
walnats/middlewares/__init__.py
walnats/middlewares/_base.py
walnats/middlewares/_integrations.py
walnats/middlewares/_middlewares.py
walnats/middlewares/_wrappers.py
walnats/serializers/__init__.py
walnats/serializers/_base.py
walnats/serializers/_optional.py
walnats/serializers/_registry.py
walnats/serializers/_serializers.py
walnats/serializers/_wrappers.py
walnats-1.2.6.dist-info/entry_points.txt
walnats-1.2.6.dist-info/LICENSE
walnats-1.2.6.dist-info/WHEEL
walnats-1.2.6.dist-info/METADATA
walnats-1.2.6.dist-info/RECORD
