Metadata-Version: 2.1
Name: walnats
Version: 1.2.6
Summary: Nats-based event-driven background jobs and microservices framework.
Keywords: nats,dramatiq,celery,microservices,rabbitmq,arq,rq,huey,event-driven,distributed
Author-email: Gram <git@orsinium.dev>
Requires-Python: >=3.8
Classifier: Development Status :: 5 - Production/Stable
Classifier: Intended Audience :: Developers
Classifier: License :: OSI Approved :: MIT License
Classifier: Programming Language :: Python
Classifier: Typing :: Typed
Requires-Dist: nats-py
Requires-Dist: sphinx ; extra == "docs"
Requires-Dist: myst-parser ; extra == "docs"
Requires-Dist: aiozipkin ; extra == "integrations"
Requires-Dist: cryptography ; extra == "integrations"
Requires-Dist: datadog ; extra == "integrations"
Requires-Dist: marshmallow ; extra == "integrations"
Requires-Dist: msgpack ; extra == "integrations"
Requires-Dist: opentelemetry-distro ; extra == "integrations"
Requires-Dist: prometheus-client ; extra == "integrations"
Requires-Dist: protobuf ; extra == "integrations"
Requires-Dist: pydantic ; extra == "integrations"
Requires-Dist: sentry-sdk ; extra == "integrations"
Requires-Dist: flake8 ; extra == "lint"
Requires-Dist: isort ; extra == "lint"
Requires-Dist: mypy ; extra == "lint"
Requires-Dist: types-protobuf ; extra == "lint"
Requires-Dist: unify ; extra == "lint"
Requires-Dist: hypothesis ; extra == "test"
Requires-Dist: pytest ; extra == "test"
Requires-Dist: pytest-cov ; extra == "test"
Requires-Dist: pytest-asyncio ; extra == "test"
Project-URL: Source, https://github.com/orsinium-labs/walnats
Provides-Extra: docs
Provides-Extra: integrations
Provides-Extra: lint
Provides-Extra: test
